core/__init__.py
SocialScraper-1.0.1.dist-info/LICENSE
SocialScraper-1.0.1.dist-info/METADATA
SocialScraper-1.0.1.dist-info/WHEEL
SocialScraper-1.0.1.dist-info/top_level.txt
SocialScraper-1.0.1.dist-info/RECORD
