Metadata-Version: 2.1
Name: SocialScraper
Version: 1.0.1
Summary: Social Scraper is a python tool meant for Detection of Child Predators/Cyber Harassers on Social Media
Home-page: https://github.com/Aravindha1234u/SocialScraper
Author: Aravindha Hariharan
Author-email: aravindha1234u@gmail.com
License: GPLv3+
Platform: UNKNOWN
Classifier: Programming Language :: Python :: 3
Classifier: License :: OSI Approved :: GNU General Public License v3 or later (GPLv3+)
Classifier: Operating System :: OS Independent
Classifier: Topic :: Software Development :: Libraries :: Python Modules
Classifier: Topic :: Security
Requires-Python: >=3.6
Requires-Dist: requests
Requires-Dist: bs4
Requires-Dist: igql
Requires-Dist: urllib3
Requires-Dist: httplib2
Requires-Dist: oauth2
Requires-Dist: selenium
Requires-Dist: apiclient
Requires-Dist: google-api-python-client (==1.5.5)
Requires-Dist: bs2json
Requires-Dist: pprint
Requires-Dist: oauth2client
Requires-Dist: jsonlib-python3
Requires-Dist: pyyaml
